TichonetDL7/DL7.py
TichonetDL7/__init__.py
tichonetdl7-0.0.1.dist-info/METADATA
tichonetdl7-0.0.1.dist-info/WHEEL
tichonetdl7-0.0.1.dist-info/licenses/LICENSE
tichonetdl7-0.0.1.dist-info/RECORD
